LICENSE
README.md
setup.py
scrapeops_scrapy_proxy_sdk/__init__.py
scrapeops_scrapy_proxy_sdk/scrapeops_scrapy_proxy_sdk.py
scrapeops_scrapy_proxy_sdk.egg-info/PKG-INFO
scrapeops_scrapy_proxy_sdk.egg-info/SOURCES.txt
scrapeops_scrapy_proxy_sdk.egg-info/dependency_links.txt
scrapeops_scrapy_proxy_sdk.egg-info/requires.txt
scrapeops_scrapy_proxy_sdk.egg-info/top_level.txt