Metadata-Version: 1.2
Name: scrapeops-scrapy-proxy-sdk
Version: 1.0
Summary: Scrapeops Scrapy Proxy SDK, simple integration to use the Scrapeops Proxy API with your Scrapy Spiders.
Home-page: https://github.com/ScrapeOps/scrapeops-scrapy-proxy-sdk
Author: ScrapeOps
Author-email: info@scrapeops.io
License: BSD
Platform: UNKNOWN
Classifier: Programming Language :: Python
Classifier: Programming Language :: Python :: 3
Classifier: Programming Language :: Python :: 3.6
Classifier: Programming Language :: Python :: 3.7
Classifier: Programming Language :: Python :: 3.8
Classifier: Programming Language :: Python :: 3.9
Classifier: Programming Language :: Python :: 3.10
Classifier: License :: OSI Approved :: BSD License
Classifier: Operating System :: OS Independent
Classifier: Intended Audience :: Developers
Requires-Python: >=3.6
